mppsolar/__init__.py
mppsolar/helpers.py
mppsolar/version.py
mppsolar/devices/__init__.py
mppsolar/devices/device.py
mppsolar/devices/jkbms.py
mppsolar/devices/mppsolar.py
mppsolar/io/__init__.py
mppsolar/io/baseio.py
mppsolar/io/dalyserialio.py
mppsolar/io/esp32io.py
mppsolar/io/hidrawio.py
mppsolar/io/jkbledelegate.py
mppsolar/io/jkbleio.py
mppsolar/io/mqttio.py
mppsolar/io/serialio.py
mppsolar/io/testio.py
mppsolar/io/vserialio.py
mppsolar/outputs/__init__.py
mppsolar/outputs/baseoutput.py
mppsolar/outputs/hass_mqtt.py
mppsolar/outputs/influx2_mqtt.py
mppsolar/outputs/influx_mqtt.py
mppsolar/outputs/json.py
mppsolar/outputs/json_mqtt.py
mppsolar/outputs/mqtt.py
mppsolar/outputs/raw.py
mppsolar/outputs/screen.py
mppsolar/outputs/tag_mqtt.py
mppsolar/protocols/__init__.py
mppsolar/protocols/abstractprotocol.py
mppsolar/protocols/daly.py
mppsolar/protocols/daly40.py
mppsolar/protocols/jk02.py
mppsolar/protocols/jk04.py
mppsolar/protocols/jk232.py
mppsolar/protocols/jk485.py
mppsolar/protocols/jkabstractprotocol.py
mppsolar/protocols/pi16.py
mppsolar/protocols/pi17.py
mppsolar/protocols/pi18.py
mppsolar/protocols/pi30.py
mppsolar/protocols/pi30max.py
mppsolar/protocols/pi30revo.py
mppsolar/protocols/pi41.py
mppsolar/protocols/protocol_helpers.py
mppsolar/protocols/ved.py
mpp_solar-0.7.76.dist-info/LICENSE
mpp_solar-0.7.76.dist-info/METADATA
mpp_solar-0.7.76.dist-info/WHEEL
mpp_solar-0.7.76.dist-info/entry_points.txt
mpp_solar-0.7.76.dist-info/top_level.txt
mpp_solar-0.7.76.dist-info/RECORD
