Metadata-Version: 2.1
Name: mpp-solar
Version: 0.7.76
Summary: Package to communicate with Solar inverters and BMSs
Home-page: https://github.com/jblance/mpp-solar
Author: John Blance
Author-email: 
License: MIT
Keywords: hardware serial communication
Platform: UNKNOWN
Classifier: Development Status :: 4 - Beta
Classifier: Intended Audience :: Developers
Classifier: License :: OSI Approved :: MIT License
Classifier: Programming Language :: Python :: 3
Classifier: Programming Language :: Python :: 3.6
Classifier: Programming Language :: Python :: 3.8
Requires-Python: >=3.6
License-File: LICENSE
Requires-Dist: pyserial
Requires-Dist: paho-mqtt
Provides-Extra: dev
Requires-Dist: check-manifest ; extra == 'dev'
Provides-Extra: test
Requires-Dist: coverage ; extra == 'test'
